MANIFEST.in
README.md
requirements.txt
setup.cfg
setup.py
versioneer.py
botcity/plugins/slack/__init__.py
botcity/plugins/slack/_version.py
botcity/plugins/slack/models.py
botcity/plugins/slack/plugin.py
botcity_slack_plugin.egg-info/PKG-INFO
botcity_slack_plugin.egg-info/SOURCES.txt
botcity_slack_plugin.egg-info/dependency_links.txt
botcity_slack_plugin.egg-info/requires.txt
botcity_slack_plugin.egg-info/top_level.txt
tests/test_import.py
tests/test_plugin.py