Metadata-Version: 2.1
Name: botcity-slack-plugin
Version: 1.0.2
Home-page: https://bitbucket.org/botcitydev/bot-slack-plugin-python.git
Requires-Python: >=3.7
